hybrid_cipher.py
hybrid_cipher-0.1.1.dist-info/LICENSE
hybrid_cipher-0.1.1.dist-info/METADATA
hybrid_cipher-0.1.1.dist-info/WHEEL
hybrid_cipher-0.1.1.dist-info/top_level.txt
hybrid_cipher-0.1.1.dist-info/RECORD
