Metadata-Version: 2.1
Name: hybrid-cipher
Version: 0.1.1
Summary: Hybrid Encryption Mode with Public-Key Encryption and Symmetric Encryption.
Home-page: UNKNOWN
Author: Zhao JunTao
Maintainer: Zhao JunTao
License: MIT
Keywords: hybrid-cipher
Platform: UNKNOWN
Classifier: Development Status :: 5 - Production/Stable
Classifier: Intended Audience :: Developers
Classifier: Topic :: Software Development :: Libraries :: Python Modules
Classifier: License :: OSI Approved :: MIT License
Classifier: Programming Language :: Python :: 3
Classifier: Programming Language :: Python :: 3 :: Only
License-File: LICENSE
Requires-Dist: PyCryptodome
